spectral_line_finder/CIE_xyz_1931_2deg.csv
spectral_line_finder/__init__.py
spectral_line_finder/app.py
spectral_line_finder/app.tcss
spectral_line_finder/cache.py
spectral_line_finder/data.py
spectral_line_finder/filter_data.py
spectral_line_finder/py.typed
spectral_line_finder/select_columns.py
spectral_line_finder/spectral_lines_table.py
spectral_line_finder/spectrum_plot.py
spectral_line_finder-0.1.0.dist-info/METADATA
spectral_line_finder-0.1.0.dist-info/WHEEL
spectral_line_finder-0.1.0.dist-info/entry_points.txt
spectral_line_finder-0.1.0.dist-info/licenses/LICENSE
spectral_line_finder-0.1.0.dist-info/RECORD
