Metadata-Version: 2.4
Name: spectral-line-finder
Version: 0.1.0
Summary: Find and match lines in spectroscopic data from NIST.
Author-email: David Fokkema <davidfokkema@icloud.com>
License-File: LICENSE
Requires-Python: >=3.12
Requires-Dist: diskcache>=5.6.3
Requires-Dist: httpx>=0.28.1
Requires-Dist: pandas>=2.3.0
Requires-Dist: platformdirs>=4.5.1
Requires-Dist: textual-plot>=0.10.0.post2
Requires-Dist: textual>=3.5.0
Requires-Dist: typer>=0.16.0
